LICENSE
MANIFEST.in
README.md
config.ini.dist
setup.py
influxdb_sysmond.egg-info/PKG-INFO
influxdb_sysmond.egg-info/SOURCES.txt
influxdb_sysmond.egg-info/dependency_links.txt
influxdb_sysmond.egg-info/entry_points.txt
influxdb_sysmond.egg-info/not-zip-safe
influxdb_sysmond.egg-info/requires.txt
influxdb_sysmond.egg-info/top_level.txt
sysmond/__init__.py
sysmond/config.py
sysmond/daemon.py
sysmond/main.py
sysmond/manager.py
sysmond/threads.py
sysmond/collectors/__init__.py
sysmond/collectors/cpu.py
sysmond/collectors/disk.py
sysmond/collectors/load.py
sysmond/collectors/memory.py
sysmond/collectors/net.py