Metadata-Version: 1.0
Name: influxdb-sysmond
Version: 0.0.6
Summary: System monitoring daemon that logs to InfluxDB
Home-page: https://github.com/EvanDarwin/InfluxDB-sysmond
Author: Evan Darwin
Author-email: evan@devil.io
License: MIT
Platform: UNKNOWN
